qat/hardware/__init__.pyd
qat/hardware/default.pyd
qat/hardware/models.pyd
qat/hardware/tomography.pyd
qat/hardware/version.pyd
qat/hardware/ions/gates_specification.pyd
qat_hardware-1.6.0.dist-info/licenses/LICENSE.txt
qat_hardware-1.6.0.dist-info/METADATA
qat_hardware-1.6.0.dist-info/WHEEL
qat_hardware-1.6.0.dist-info/top_level.txt
qat_hardware-1.6.0.dist-info/RECORD
