Metadata-Version: 2.4
Name: qat-hardware
Version: 1.6.0
Summary: Module qat-hardware [83d8047] - Compiled by Eviden
Home-page: https://atos.net/en/lp/myqlm
Author: Eviden Quantum Lab
Author-email: myqlm@atos.net
License: Eviden myQLM EULA
Project-URL: Documentation, https://myqlm.github.io
Project-URL: Bug Tracker, https://github.com/myQLM/myqlm-issues/issues
Project-URL: Community, https://myqlmworkspace.slack.com
Keywords: Quantum,myQLM,QLM,Atos,Eviden
Platform: Operating System :: MacOS :: MacOS X
Classifier: Operating System :: MacOS :: MacOS X
Classifier: Programming Language :: Python :: 3.1
Classifier: Topic :: Scientific/Engineering
Classifier: License :: Other/Proprietary License
License-File: LICENSE.txt
Requires-Dist: qutip
Requires-Dist: numpy
Requires-Dist: qat-comm
Requires-Dist: qat-core
Requires-Dist: qat-lang
Dynamic: author
Dynamic: author-email
Dynamic: classifier
Dynamic: description
Dynamic: description-content-type
Dynamic: home-page
Dynamic: keywords
Dynamic: license
Dynamic: license-file
Dynamic: platform
Dynamic: project-url
Dynamic: requires-dist
Dynamic: summary
